{
    "ObjectCount": 5,
    "Objects": [
        {
            "Name": "JSONPlayer",
            "Type": "Player",
            "Components": {
                "PhysicsBody": {
                    "VelocityX": -337.8252258300781,
                    "VelocityY": -150.10238647460938,
                    "RotationSpeed": 200.0,
                    "Speed": 50.0
                },
                "Transform": {
                    "PositionX": -1450.6146240234375,
                    "PositionY": -631.6143188476563,
                    "Rotation": -109.58076477050781,
                    "Scale": 200.0
                }
            }
        },
        {
            "Name": "JSONEnemy1",
            "Type": "Enemy",
            "Components": {
                "PhysicsBody": {
                    "VelocityX": 0.0,
                    "VelocityY": 0.0,
                    "RotationSpeed": 20.0,
                    "Speed": 700.0
                },
                "Transform": {
                    "PositionX": 50.0,
                    "PositionY": -200.0,
                    "Rotation": 261.0159912109375,
                    "Scale": 130.0
                }
            }
        },
        {
            "Name": "JSONEnemy2",
            "Type": "Enemy",
            "Components": {
                "PhysicsBody": {
                    "VelocityX": 0.0,
                    "VelocityY": 0.0,
                    "RotationSpeed": 20.0,
                    "Speed": 500.0
                },
                "Transform": {
                    "PositionX": 200.0,
                    "PositionY": 100.0,
                    "Rotation": 261.0159912109375,
                    "Scale": 220.0
                }
            }
        },
        {
            "Name": "PlayerObjFromPrefab",
            "Type": "Player",
            "Components": {
                "PhysicsBody": {
                    "VelocityX": 0.0,
                    "VelocityY": 0.0,
                    "RotationSpeed": 0.0,
                    "Speed": 50.0
                },
                "Transform": {
                    "PositionX": -250.0,
                    "PositionY": 50.0,
                    "Rotation": 0.0,
                    "Scale": 100.0
                }
            }
        },
        {
            "Name": "Object5",
            "Type": "Player",
            "Components": {
                "PhysicsBody": {
                    "VelocityX": 1228.74365234375,
                    "VelocityY": 0.0,
                    "RotationSpeed": 200.0,
                    "Speed": 50.0
                },
                "Transform": {
                    "PositionX": -1422.3203125,
                    "PositionY": 50.0,
                    "Rotation": 189.66934204101563,
                    "Scale": 200.0
                },
                "None": {}
            }
        }
    ]
}
